fvdb/__init__.py
fvdb/cli.hy
fvdb/config.py
fvdb/db.hy
fvdb/embeddings.hy
fvdb/split.hy
fvdb/summaries.hy
fvdb-0.1.7.dist-info/licenses/LICENSE
fvdb-0.1.7.dist-info/METADATA
fvdb-0.1.7.dist-info/WHEEL
fvdb-0.1.7.dist-info/entry_points.txt
fvdb-0.1.7.dist-info/top_level.txt
fvdb-0.1.7.dist-info/RECORD
