Metadata-Version: 2.4
Name: fvdb
Version: 0.1.7
Summary: Thin porcelain around the FAISS vector database.
Author-email: Ati Sharma <ati+fvdb@agalmic.ltd>
License:                     GNU AFFERO GENERAL PUBLIC LICENSE
Project-URL: Repository, https://github.com/atisharma/fvdb
Keywords: hy,hylang
Classifier: Development Status :: 4 - Beta
Classifier: License :: OSI Approved :: GNU Affero General Public License v3 or later (AGPLv3+)
Classifier: Programming Language :: Python :: 3
Classifier: Programming Language :: Python :: 3.11
Classifier: Programming Language :: Python :: 3.12
Classifier: Programming Language :: Python :: 3.13
Requires-Python: >=3.11
License-File: LICENSE
Requires-Dist: click
Requires-Dist: faiss-cpu
Requires-Dist: hy
Requires-Dist: hyjinx
Requires-Dist: hyrule
Requires-Dist: markdownify
Requires-Dist: platformdirs
Requires-Dist: sentence-transformers
Requires-Dist: sumy
Requires-Dist: tabulate
Requires-Dist: tiktoken
Requires-Dist: toolz
Dynamic: license-file
